GreenLightPlus/README.md
GreenLightPlus/__init__.py
GreenLightPlus/core/green_light_model.py
GreenLightPlus/core/greenhouse_env.py
GreenLightPlus/core/greenhouse_geometry.py
GreenLightPlus/core/greenlight_energyplus_simulation.py
GreenLightPlus/create_green_light_model/change_res.py
GreenLightPlus/create_green_light_model/create_green_light_model.py
GreenLightPlus/create_green_light_model/ode.py
GreenLightPlus/create_green_light_model/set_default_lamp_params.py
GreenLightPlus/create_green_light_model/set_dep_params.py
GreenLightPlus/create_green_light_model/set_gl_aux.py
GreenLightPlus/create_green_light_model/set_gl_control.py
GreenLightPlus/create_green_light_model/set_gl_control_init.py
GreenLightPlus/create_green_light_model/set_gl_odes.py
GreenLightPlus/create_green_light_model/set_gl_params.py
GreenLightPlus/create_green_light_model/set_gl_states.py
GreenLightPlus/create_green_light_model/set_gl_states_init.py
GreenLightPlus/create_green_light_model/set_gl_time.py
GreenLightPlus/create_green_light_model/set_gl_weather.py
GreenLightPlus/create_green_light_model/set_params4ha_world_comparison.py
GreenLightPlus/result_analysis/energy_analysis.py
GreenLightPlus/result_analysis/energy_yield_analysis.py
GreenLightPlus/result_analysis/plot_green_light.py
GreenLightPlus/service_functions/co2_dens2ppm.py
GreenLightPlus/service_functions/co2_ppm2dens.py
GreenLightPlus/service_functions/convert_epw2csv.py
GreenLightPlus/service_functions/cut_energy_plus_data.py
GreenLightPlus/service_functions/day_light_sum.py
GreenLightPlus/service_functions/funcs.py
GreenLightPlus/service_functions/make_artificial_input.py
GreenLightPlus/service_functions/rh2vapor_dens.py
GreenLightPlus/service_functions/vapor_dens2pres.py
GreenLightPlus/service_functions/vp2dens.py
GreenLightPlus-2.5.dist-info/METADATA
GreenLightPlus-2.5.dist-info/WHEEL
GreenLightPlus-2.5.dist-info/entry_points.txt
GreenLightPlus-2.5.dist-info/top_level.txt
GreenLightPlus-2.5.dist-info/RECORD
